Workbook

Sheet Summary
A1: Sprint Backlog Summary
A2: Auto-reconciled with Project Budget · Total target: 1,236 hours
A4: Sprint | B4: Planning Mode | C4: Tasks | D4: Hours Planned | E4: % of Budget
A5: Sprint 1 | B5: Detailed | C5: 16 | D5: =Backlog!C19 -> 164 | E5: =D5/1236 -> 0.13268608
A6: Sprint 2 | B6: Detailed | C6: 17 | D6: =Backlog!C40 -> 224 | E6: =D6/1236 -> 0.18122977
A7: Sprint 3 | B7: Detailed | C7: 18 | D7: =Backlog!C67 -> 278 | E7: =D7/1236 -> 0.22491909
A8: Sprint 4 | B8: High-level (rolling wave) | C8: 12 | D8: =Backlog!C88 -> 186 | E8: =D8/1236 -> 0.15048544
A9: Sprint 5 | B9: High-level (rolling wave) | C9: 9 | D9: =Backlog!C99 -> 146 | E9: =D9/1236 -> 0.11812298
A10: Total | C10: =SUM(C5:C9) -> 72 | D10: =SUM(D5:D9) -> 998 | E10: =D10/1236 -> 0.80744337
A12: Budget target | D12: 1236
A13: Variance | D13: =D10-D12 -> -238

Sheet Backlog
B1: COMP47360 Research Practicum — Sprint Backlog
B3: Sprint 1
A4: Epic | B4: Task | C4: Estimated Hours | D4: Real Hours | E4: Completion Date | F4: Nancy | G4: Hansel | H4: Alison | I4: Eoin | J4: Sean | K4: Status | L4: Budget Category
A5: PM | B5: Personas & interviews | C5: 16 | D5: 16 | E5: 46167 | F5: TRUE | G5: TRUE | H5: TRUE | I5: TRUE | J5: TRUE | K5: Completed | L5: 1. Requirements & Research
A6: PM | B6: Research competitors | C6: 8 | D6: 6 | E6: 46167 | F6: TRUE | G6: TRUE | H6: TRUE | I6: TRUE | J6: TRUE | K6: Completed | L6: 1. Requirements & Research
A7: PM | B7: Develop early prototypes & mockups | C7: 12 | D7: 12 | E7: 46170 | F7: TRUE | G7: TRUE | H7: TRUE | I7: TRUE | J7: TRUE | K7: Completed | L7: 2. Design (UX/UI)
A8: Infra | B8: Select technologies | C8: 8 | D8: 5 | E8: 46171 | G8: TRUE | H8: TRUE | I8: TRUE | J8: TRUE | K8: Completed | L8: 3. Backend Development
A9: PM | B9: Define user stories & acceptance criteria | C9: 16 | D9: 16 | E9: 46175 | F9: TRUE | K9: Completed | L9: 10. Project Management
A10: PM | B10: Create budget | C10: 10 | D10: 8 | E10: 46171 | F10: TRUE | K10: Completed | L10: 10. Project Management
A11: Infra | B11: Create GitHub Repository | C11: 4 | D11: 5 | E11: 46168 | G11: TRUE | K11: Completed | L11: 9. Deployment & DevOps
A12: Infra | B12: Define Git workflow | C12: 6 | D12: 4 | E12: 46168 | G12: TRUE | K12: Completed | L12: 9. Deployment & DevOps
A13: ML / Data | B13: Crowd data feasibility spike (NYC Open Data) | C13: 24 | D13: 24 | E13: 46178 | H13: TRUE | K13: Completed | L13: 6. ML / Data Engineering
A14: Infra | B14: React-Vite + TypeScript env | C14: 12 | D14: 12 | E14: 46167 | I14: TRUE | K14: Completed | L14: 4. Web Frontend
A15: Infra | B15: Mobile env | C15: 12 | D15: 10 | E15: 46178 | J15: TRUE | K15: Completed | L15: 5. Mobile Development
A16: Auth | B16: Initial frontend structure (no features) | C16: 8 | D16: 8 | E16: 46177 | I16: TRUE | J16: TRUE | K16: Completed | L16: 4. Web Frontend
A17: Infra | B17: Initialise FastAPI backend env | C17: 12 | D17: 12 | E17: 46175 | G17: TRUE | K17: Completed | L17: 3. Backend Development
A18: PM | B18: UX strategy (web vs mobile differentiation) | C18: 16 | D18: 26 | E18: 46176 | F18: TRUE | J18: TRUE | K18: Completed | L18: 2. Design (UX/UI)
B19: Sprint 1 Total | C19: =SUM(C5:C18) -> 164 | D19: =SUM(D5:D18) -> 164
B21: Sprint 2
A22: Epic | B22: Task | C22: Estimated Hours | D22: Real Hours | E22: Completion Date | F22: Nancy | G22: Hansel | H22: Alison | I22: Eoin | J22: Sean | K22: Status | L22: Budget Category
A23: Auth | B23: Auth API setup (Firebase) | C23: 16 | D23: 16 | E23: 46185 | G23: TRUE | K23: Completed | L23: 3. Backend Development
A24: Auth | B24: Auth flow UI (Web) | C24: 12 | D24: 12 | E24: 46189 | I24: TRUE | K24: Completed | L24: 4. Web Frontend
A25: Auth | B25: Bottom navigation component (Web) | C25: 8 | D25: 8 | E25: 46189 | I25: TRUE | K25: Completed | L25: 4. Web Frontend
A26: Auth | B26: Auth flow + Nav (Mobile) | C26: 16 | D26: 16 | E26: 46189 | J26: TRUE | K26: Completed | L26: 5. Mobile Development
A27: Explore | B27: POI database schema + initial 30 POIs | C27: 20 | D27: 20 | E27: 46196 | G27: TRUE | K27: Completed | L27: 3. Backend Development
A28: Explore | B28: GET /pois + GET /poi/{id} endpoints | C28: 12 | D28: 12 | E28: 46189 | G28: TRUE | K28: Completed | L28: 3. Backend Development
A29: Explore | B29: POI popularity flag + Save/Unsave POI API endpoints | C29: 4 | D29: 4 | E29: 46192 | G29: TRUE | K29: Completed | L29: 3. Backend Development
A30: Explore | B30: Explore tab UI + Save icon on POI cards (Web) | C30: 16 | D30: 16 | E30: 46190 | I30: TRUE | K30: Completed | L30: 4. Web Frontend
A31: Explore | B31: POI Detail page UI (Web) | C31: 16 | D31: 16 | E31: 46190 | I31: TRUE | K31: Completed | L31: 4. Web Frontend
A32: Explore | B32: Explore tab + POI Detail (Mobile) | C32: 28 | D32: 24 | E32: 46203 | J32: TRUE | K32: Completed | L32: 5. Mobile Development
A33: ML / Data | B33: Provide data quality report | C33: 16 | D33: 16 | E33: 46190 | H33: TRUE | K33: Completed | L33: 6. ML / Data Engineering
A34: ML / Data | B34: Provide peliminary integrated dataset | C34: 24 | D34: 24 | E34: 46191 | H34: TRUE | K34: Completed | L34: 6. ML / Data Engineering
A35: My Itinerary | B35: My Itinerary tab shell + date picker (Web) | C35: 8 | D35: 8 | E35: 46192 | I35: TRUE | K35: Completed | L35: 4. Web Frontend
A36: My Itinerary | B36: My Itinerary tab shell + date picker (Mobile) | C36: 6 | D36: 6 | E36: 46203 | J36: TRUE | K36: Completed | L36: 5. Mobile Development
A37: PM | B37: Sprint 2 ceremonies + retro | C37: 6 | D37: 6 | E37: 46192 | F37: TRUE | K37: Completed | L37: 10. Project Management
A38: PM | B38: Mid-fidelity wireframes (AI-accelerated, 4 core screens) | C38: 16 | D38: 16 | E38: 46189 | F38: TRUE | K38: Completed | L38: 2. Design (UX/UI)
A39: AI Planner | B39: AI Planner Spike — API + session memory POC | C39: 6 | D39: 6 | E39: 46198 | F39: TRUE | K39: Completed | L39: 6. ML / Data Engineering
B40: Sprint 2 Total | C40: =sum(C23:C38) -> 224 | D40: =sum(D23:D39) -> 226
B42: Sprint 3
A43: Epic | B43: Task | C43: Estimated Hours | D43: Real Hours | E43: Completion Date | F43: Nancy | G43: Hansel | H43: Alison | I43: Eoin | J43: Sean | K43: Status | L43: Budget Category
A44: Explore | B44: Map POIs to nearest subway station | C44: 6 | D44: 6 | E44: 46205 | G44: TRUE | K44: Completed | L44: 3. Backend Development
A45: Explore | B45: Fallback msg: Crowd Forecast (no POI data) | C45: 4 | D45: 4 | E45: 46206 | G45: TRUE | I45: TRUE | J45: TRUE | K45: Completed | L45: 4. Web Frontend
A46: Explore | B46: POI database schema + initial 30 POIs [Carryover] | C46: 20 | D46: 20 | E46: 46198 | G46: TRUE | K46: Completed | L46: 3. Backend Development
A47: Explore | B47: Crowd Forecast chart UI (Web) | C47: 8 | D47: 8 | E47: 46198 | I47: TRUE | K47: Completed | L47: 4. Web Frontend
A48: Explore | B48: Crowd Forecast chart UI (Mobile) | C48: 8 | D48: 8 | E48: 46203 | J48: TRUE | K48: Completed | L48: 5. Mobile Development
A49: ML / Data | B49: Finalised busyness formula and result grade | C49: 12 | D49: 12 | E49: 46198 | H49: TRUE | K49: Completed | L49: 6. ML / Data Engineering
A50: ML / Data | B50: ML preparation: Training plan, initial result | C50: 20 | D50: 20 | E50: 46204 | H50: TRUE | K50: Completed | L50: 6. ML / Data Engineering
A51: My Itinerary | B51: Itinerary generation core engine (Rule-based & AI core scheduling logic) | C51: 20 | D51: 20 | E51: 46204 | G51: TRUE | K51: Completed | L51: 6. ML / Data Engineering
A52: My Itinerary | B52: Crowd data integration + Itinerary Generation & Update API endpoints | C52: 16 | D52: 16 | E52: 46204 | G52: TRUE | K52: Completed | L52: 6. ML / Data Engineering
A53: My Itinerary | B53: 5 POI/day + geographic proximity allocation algorithm | C53: 12 | D53: 28 | E53: 46210 | G53: TRUE | K53: Completed | L53: 6. ML / Data Engineering
A54: My Itinerary | B54: My Itinerary 4-section UI (Search/Selected/Saved/Popular) — Web | C54: 20 | D54: 20 | E54: 46204 | I54: TRUE | K54: Completed | L54: 4. Web Frontend
A55: My Itinerary | B55: Itinerary view page (scheduled output) — Web | C55: 16 | D55: 16 | E55: 46204 | I55: TRUE | K55: Completed | L55: 4. Web Frontend
A56: My Itinerary | B56: "Why this time" UI integration (Web) | C56: 6 | D56: 6 | E56: 46199 | I56: TRUE | K56: Completed | L56: 4. Web Frontend
A57: My Itinerary | B57: Loading & error states (Web) | C57: 6 | D57: 6 | E57: 46199 | I57: TRUE | K57: Completed | L57: 4. Web Frontend
A58: My Itinerary | B58: Itinerary view (Infinite scroll scheduled output) — Mobile | C58: 24 | D58: 6 | E58: 46199 | J58: TRUE | K58: Completed | L58: 5. Mobile Development
A59: My Itinerary | B59: "Why this time" + states (Mobile) | C59: 16 | D59: 6 | E59: 46199 | J59: TRUE | K59: Completed | L59: 5. Mobile Development
A60: My Itinerary | B60: Itinerary Editor (Dropdown Pill time-change & Hover-remove) — Web | C60: 12 | D60: 12 | E60: 46199 | I60: TRUE | K60: In Progress | L60: 4. Web Frontend
A61: My Itinerary | B61: My Itinerary 4-section UI (Mobile) | C61: 20 | D61: 6 | E61: 46199 | J61: TRUE | K61: Completed | L61: 5. Mobile Development
A62: My Itinerary | B62: Fallback msg: "Why this time" (no ML data) | C62: 6 | D62: 6 | E62: 46199 | G62: TRUE | I62: TRUE | J62: TRUE | K62: Completed | L62: 4. Web Frontend
A63: PM | B63: High-fi mockups (AI-accelerated, core flow) | C63: 10 | D63: 10 | E63: 46204 | F63: TRUE | K63: Completed | L63: 2. Design (UX/UI)
A64: PM | B64: Polish edge cases + empty states | C64: 6 | D64: 6 | E64: 46204 | F64: TRUE | K64: Completed | L64: 4. Web Frontend
A65: PM | B65: User testing prep | C65: 4 | D65: 4 | E65: 46206 | F65: TRUE | K65: Completed | L65: 8. Testing & QA
A66: PM | B66: Sprint 3 ceremonies + retro | C66: 6 | D66: 6 | E66: 46206 | F66: TRUE | K66: Completed | L66: 10. Project Management
B67: Sprint 3 Total | C67: =SUM(C43:C66) -> 278 | D67: =SUM(D43:D66) -> 252
B69: Sprint 4
B70: Task | C70: Estimated Hours | D70: Real Hours | E70: Completion Date | F70: Nancy | G70: Hansel | H70: Alison | I70: Eoin | J70: Sean | K70: Status | L70: Budget Category
A71: Explore | B71: Filter POIs by interest / accessibility | C71: 16 | D71: 16 | E71: 46214 | I71: TRUE | J71: TRUE | K71: Completed | L71: 4. Web Frontend
A72: Profile | B72: Profile tab (Web) | C72: 4 | D72: 4 | E72: 46216 | I72: TRUE | K72: Completed | L72: 4. Web Frontend
A73: Profile | B73: Profile tab (Mobile) | C73: 4 | D73: 4 | E73: 46211 | J73: TRUE | K73: Completed | L73: 5. Mobile Development
A74: AI Planner | B74: AI Planner backend (Gemini + session memory) | C74: 16 | D74: 16 | E74: 46216 | G74: TRUE | K74: Completed | L74: 6. ML / Data Engineering
A75: AI Planner | B75: AI Planner UI (Web) | C75: 12 | D75: 12 | E75: 46216 | I75: TRUE | K75: Completed | L75: 4. Web Frontend
A76: AI Planner | B76: AI Planner UI (Mobile) | C76: 12 | D76: 12 | E76: 46217 | J76: TRUE | K76: Completed | L76: 5. Mobile Development
A77: Infra | B77: Deployment | C77: 12 | D77: 12 | E77: 46216 | H77: TRUE | K77: Completed | L77: 9. Deployment & DevOps
A78: Infra | B78: Database setup (PostGIS) | C78: 16 | D78: 16 | E78: 46218 | G78: TRUE | K78: Completed | L78: 3. Backend Development
A79: ML / Data | B79: Evaluate ML model (metrics, validation) | C79: 12 | D79: 12 | E79: 46219 | H79: TRUE | K79: Completed | L79: 6. ML / Data Engineering
A80: ML / Data | B80: Integrate ML predictions with backend | C80: 12 | D80: 12 | E80: 46218 | G80: TRUE | H80: TRUE | K80: Completed | L80: 6. ML / Data Engineering
A81: My Itinerary | B81: In-line Itinerary Editor — Mobile | C81: 6 | D81: 6 | E81: 46220 | J81: TRUE | K81: Completed | L81: 5. Mobile Development
A82: Saved | B82: Saved tab functional (Web) | C82: 8 | D82: 8 | E82: 46211 | I82: TRUE | K82: Completed | L82: 4. Web Frontend
A83: Saved | B83: Saved tab functional (Mobile) | C83: 8 | D83: 8 | E83: 46211 | J83: TRUE | K83: Completed | L83: 5. Mobile Development
A84: PM | B84: UAT Test | C84: 30 | D84: 30 | E84: 46214 | F84: TRUE | K84: Completed | L84: 8. Testing & QA
A85: PM | B85: Unit Test | C85: 16 | D85: 16 | E85: 46216 | F85: TRUE | K85: Completed | L85: 8. Testing & QA
A86: PM | B86: Literature review | C86: 20 | D86: 20 | E86: 46211 | F86: TRUE | K86: Completed | L86: 1. Requirements & Research
A87: PM | B87: Sprint 4 ceremonies + retro | C87: 6 | D87: 6 | E87: 46217 | F87: TRUE | K87: Completed | L87: 10. Project Management
B88: Sprint 4 Total | C88: =sum(C74:C87) -> 186 | D88: =SUM(D70:D87) -> 210
B90: Sprint 5
B91: Task | C91: Estimated Hours | D91: Real Hours | E91: Completion Date | F91: Nancy | G91: Hansel | H91: Alison | I91: Eoin | J91: Sean | K91: Status | L91: Budget Category
A92: Infra | B92: Performance optimization | C92: 16 | D92: 16 | E92: 46224 | F92: TRUE | G92: TRUE | H92: TRUE | I92: TRUE | J92: TRUE | K92: Completed | L92: 3. Backend Development
A93: PM | B93: Final user testing + iterations | C93: 24 | D93: 24 | E93: 46230 | F93: TRUE | K93: Completed | L93: 8. Testing & QA
A94: PM | B94: Demo preparation + rehearsal | C94: 16 | D94: 16 | E94: 46229 | F94: TRUE | H94: TRUE | I94: TRUE | J94: TRUE | K94: Completed | L94: 10. Project Management
A95: PM | B95: Final paper writing | C95: 60 | D95: 60 | E95: 46234 | F95: TRUE | G95: TRUE | H95: TRUE | I95: TRUE | J95: TRUE | K95: Completed | L95: 10. Project Management
A96: PM | B96: Documentation cleanup | C96: 12 | D96: 12 | E96: 46231 | F96: TRUE | G96: TRUE | H96: TRUE | I96: TRUE | J96: TRUE | K96: Completed | L96: 10. Project Management
A97: Infra | B97: Final deployment + monitoring | C97: 12 | D97: 12 | E97: 46230 | H97: TRUE | K97: Completed | L97: 9. Deployment & DevOps
A98: PM | B98: Sprint 5 ceremonies + final retro | C98: 6 | D98: 6 | E98: 46234 | F98: TRUE | K98: Completed | L98: 10. Project Management
B99: Sprint 5 Total | C99: =sum(C92:C98) -> 146 | D99: 146

Sheet Burndown chart
A1: Sprint 1 Burndown Chart
A2: Sprint 1: 25 May - 05 Jun 2026 · Total planned: 204h · Working days: 10
A6: Day | B6: Date | C6: Story point | D6: Done Today | E6: Cumulative Done | F6: Actual Remaining
A7: 0 | B7: 46166 | C7: =B20 -> 40 | D7: 0 | E7: 0 | F7: =B20 -> 40
A8: 1 | B8: 46167 | C8: =$B$20-($B$20/10*A8) -> 36 | D8: 8 | E8: =E7+D8 -> 8 | F8: =$F$7-E8 -> 32
A9: 2 | B9: 46168 | C9: =$B$20-($B$20/10*A9) -> 32 | D9: 3 | E9: =E8+D9 -> 11 | F9: =$F$7-E9 -> 29
A10: 3 | B10: 46169 | C10: =$B$20-($B$20/10*A10) -> 28 | D10: 0 | E10: =E9+D10 -> 11 | F10: =$F$7-E10 -> 29
A11: 4 | B11: 46170 | C11: =$B$20-($B$20/10*A11) -> 24 | D11: 3 | E11: =E10+D11 -> 14 | F11: =$F$7-E11 -> 26
A12: 5 | B12: 46171 | C12: =$B$20-($B$20/10*A12) -> 20 | D12: 4 | E12: =E11+D12 -> 18 | F12: =$F$7-E12 -> 22
A13: 6 | B13: 46174 | C13: =$B$20-($B$20/10*A13) -> 16 | D13: 0 | E13: =E12+D13 -> 18 | F13: =$F$7-E13 -> 22
A14: 7 | B14: 46175 | C14: =$B$20-($B$20/10*A14) -> 12 | D14: 5 | E14: =E13+D14 -> 23 | F14: =$F$7-E14 -> 17
A15: 8 | B15: 46176 | C15: =$B$20-($B$20/10*A15) -> 8 | D15: 6 | E15: =E14+D15 -> 29 | F15: =$F$7-E15 -> 11
A16: 9 | B16: 46177 | C16: =$B$20-($B$20/10*A16) -> 4 | D16: 2 | E16: =E15+D16 -> 31 | F16: =$F$7-E16 -> 9
A17: 10 | B17: 46178 | C17: =$B$20-($B$20/10*A17) -> 0 | D17: 9 | E17: =E16+D17 -> 40 | F17: =$F$7-E17 -> 0
A19: Summary
A20: Total Story point | B20: 40
A21: Total Completed | B21: =E17 -> 40
A22: Remaining | B22: =C7-E17 -> 0
A23: Completion % | B23: =E17/C7 -> 1
A53: Sprint 2 Burndown Chart
A54: Sprint 1: 08 Jun 2026 - 19 Jun 2026
A58: Day | B58: Date | C58: Story point | D58: Done Today | E58: Cumulative Done | F58: Actual Remaining
A59: 0 | B59: 46180 | C59: =B72 -> 44 | D59: 0 | E59: 0 | F59: =B72 -> 44
A60: 1 | B60: 46181 | C60: =$B$72-($B$72/10*A60) -> 39.6 | E60: =E59+D60 -> 0 | F60: =$F$59-E60 -> 44
A61: 2 | B61: 46182 | C61: =$B$20-($B$20/10*A61) -> 32 | E61: =E60+D61 -> 0 | F61: =$F$59-E61 -> 44
A62: 3 | B62: 46183 | C62: =$B$20-($B$20/10*A62) -> 28 | E62: =E61+D62 -> 0 | F62: =$F$59-E62 -> 44
A63: 4 | B63: 46184 | C63: =$B$20-($B$20/10*A63) -> 24 | E63: =E62+D63 -> 0 | F63: =$F$59-E63 -> 44
A64: 5 | B64: 46185 | C64: =$B$20-($B$20/10*A64) -> 20 | D64: 3 | E64: =E63+D64 -> 3 | F64: =$F$59-E64 -> 41
A65: 6 | B65: 46188 | C65: =$B$20-($B$20/10*A65) -> 16 | E65: =E64+D65 -> 3 | F65: =$F$59-E65 -> 41
A66: 7 | B66: 46189 | C66: =$B$20-($B$20/10*A66) -> 12 | D66: 12 | E66: =E65+D66 -> 15 | F66: =$F$59-E66 -> 29
A67: 8 | B67: 46190 | C67: =$B$20-($B$20/10*A67) -> 8 | D67: 9 | E67: =E66+D67 -> 24 | F67: =$F$59-E67 -> 20
A68: 9 | B68: 46191 | C68: =$B$20-($B$20/10*A68) -> 4 | D68: 5 | E68: =E67+D68 -> 29 | F68: =$F$59-E68 -> 15
A69: 10 | B69: 46192 | C69: =$B$20-($B$20/10*A69) -> 0 | D69: 4 | E69: =E68+D69 -> 33 | F69: =$F$59-E69 -> 11
A71: Summary
A72: Total Story point | B72: 44
A73: Total Completed | B73: =E69 -> 33
A74: Remaining | B74: =B72-E69 -> 11
A75: Completion % | B75: =E69/C59 -> 0.75
A106: Sprint 3 Burndown Chart
A107: Sprint 1: 22 Jun 2026 - 3 July 2026
A111: Day | B111: Date | C111: Story point | D111: Done Today | E111: Cumulative Done | F111: Actual Remaining
A112: 0 | B112: 46194 | C112: =B125 -> 57 | D112: 0 | E112: 0 | F112: =B125 -> 57
A113: 1 | B113: 46195 | C113: =$B$125-($B$125/10*A113) -> 51.3 | E113: =E112+D113 -> 0 | F113: =$F$112-E113 -> 57
A114: 2 | B114: 46196 | C114: =$B$125-($B$125/10*A114) -> 45.6 | E114: =E113+D114 -> 0 | F114: =$F$112-E114 -> 57
A115: 3 | B115: 46197 | C115: =$B$125-($B$125/10*A115) -> 39.9 | E115: =E114+D115 -> 0 | F115: =$F$112-E115 -> 57
A116: 4 | B116: 46198 | C116: =$B$125-($B$125/10*A116) -> 34.2 | D116: 8 | E116: =E115+D116 -> 8 | F116: =$F$112-E116 -> 49
A117: 5 | B117: 46199 | C117: =$B$125-($B$125/10*A117) -> 28.5 | D117: 2 | E117: =E116+D117 -> 10 | F117: =$F$112-E117 -> 47
A118: 6 | B118: 46202 | C118: =$B$125-($B$125/10*A118) -> 22.8 | E118: =E117+D118 -> 10 | F118: =$F$112-E118 -> 47
A119: 7 | B119: 46203 | C119: =$B$125-($B$125/10*A119) -> 17.1 | D119: 2 | E119: =E118+D119 -> 12 | F119: =$F$112-E119 -> 45
A120: 8 | B120: 46204 | C120: =$B$125-($B$125/10*A120) -> 11.4 | D120: 17 | E120: =E119+D120 -> 29 | F120: =$F$112-E120 -> 28
A121: 9 | B121: 46205 | C121: =$B$125-($B$125/10*A121) -> 5.7 | E121: =E120+D121 -> 29 | F121: =$F$112-E121 -> 28
A122: 10 | B122: 46206 | C122: =$B$125-($B$125/10*A122) -> 0 | D122: 10 | E122: =E121+D122 -> 39 | F122: =$F$112-E122 -> 18
A124: Summary
A125: Total Story point | B125: 57
A126: Total Completed | B126: =E122 -> 39
A127: Remaining | B127: =B125-E122 -> 18
A128: Completion % | B128: =E122/B125 -> 0.68421053
A159: Sprint 4 Burndown Chart
A160: Sprint 4: 6 Jul 2026 - 17 Jul 2026
A164: Day | B164: Date | C164: Story point | D164: Done Today | E164: Cumulative Done | F164: Actual Remaining
A165: 0 | B165: 46208 | C165: =B178 -> 43 | D165: 0 | E165: 0 | F165: =B178 -> 43
A166: 1 | B166: 46209 | C166: =$B$178-($B$178/10*A166) -> 38.7 | D166: 0 | E166: =E165+D166 -> 0 | F166: =$F$165-E166 -> 43
A167: 2 | B167: 46210 | C167: =$B$178-($B$178/10*A167) -> 34.4 | D167: 0 | E167: =E166+D167 -> 0 | F167: =$F$165-E167 -> 43
A168: 3 | B168: 46211 | C168: =$B$178-($B$178/10*A168) -> 30.1 | D168: 5 | E168: =E167+D168 -> 5 | F168: =$F$165-E168 -> 38
A169: 4 | B169: 46212 | C169: =$B$178-($B$178/10*A169) -> 25.8 | D169: 4 | E169: =E168+D169 -> 9 | F169: =$F$165-E169 -> 34
A170: 5 | B170: 46213 | C170: =$B$178-($B$178/10*A170) -> 21.5 | D170: 4 | E170: =E169+D170 -> 13 | F170: =$F$165-E170 -> 30
A171: 6 | B171: 46216 | C171: =$B$178-($B$178/10*A171) -> 17.2 | D171: 8 | E171: =E170+D171 -> 21 | F171: =$F$165-E171 -> 22
A172: 7 | B172: 46217 | C172: =$B$178-($B$178/10*A172) -> 12.9 | D172: 6 | E172: =E171+D172 -> 27 | F172: =$F$165-E172 -> 16
A173: 8 | B173: 46218 | C173: =$B$178-($B$178/10*A173) -> 8.6 | D173: 6 | E173: =E172+D173 -> 33 | F173: =$F$165-E173 -> 10
A174: 9 | B174: 46219 | C174: =$B$178-($B$178/10*A174) -> 4.3 | D174: 4 | E174: =E173+D174 -> 37 | F174: =$F$165-E174 -> 6
A175: 10 | B175: 46220 | C175: =$B$178-($B$178/10*A175) -> 0 | D175: 6 | E175: =E174+D175 -> 43 | F175: =$F$165-E175 -> 0
A177: Summary
A178: Total Story point | B178: 43
A179: Total Completed | B179: =E175 -> 43
A180: Remaining | B180: =B178-E175 -> 0
A181: Completion % | B181: =E175/B178 -> 1
A212: Sprint 5 Burndown Chart
A213: Sprint 5: 20 Jul 2026 - 31 Jul 2026
A217: Day | B217: Date | C217: Story point | D217: Done Today | E217: Cumulative Done | F217: Actual Remaining
A218: 0 | B218: 46222 | C218: =B231 -> 19 | D218: 0 | E218: 0 | F218: =B231 -> 19
A219: 1 | B219: 46223 | C219: =$B$231-($B$231/10*A219) -> 17.1 | D219: 0 | E219: =E218+D219 -> 0 | F219: =$F$218-E219 -> 19
A220: 2 | B220: 46224 | C220: =$B$231-($B$231/10*A220) -> 15.2 | D220: 3 | E220: =E219+D220 -> 3 | F220: =$F$218-E220 -> 16
A221: 3 | B221: 46225 | C221: =$B$231-($B$231/10*A221) -> 13.3 | D221: 4 | E221: =E220+D221 -> 7 | F221: =$F$218-E221 -> 12
A222: 4 | B222: 46226 | C222: =$B$231-($B$231/10*A222) -> 11.4 | D222: 2 | E222: =E221+D222 -> 9 | F222: =$F$218-E222 -> 10
A223: 5 | B223: 46227 | C223: =$B$231-($B$231/10*A223) -> 9.5 | D223: 2 | E223: =E222+D223 -> 11 | F223: =$F$218-E223 -> 8
A224: 6 | B224: 46230 | C224: =$B$231-($B$231/10*A224) -> 7.6 | D224: 2 | E224: =E223+D224 -> 13 | F224: =$F$218-E224 -> 6
A225: 7 | B225: 46231 | C225: =$B$231-($B$231/10*A225) -> 5.7 | D225: 2 | E225: =E224+D225 -> 15 | F225: =$F$218-E225 -> 4
A226: 8 | B226: 46232 | C226: =$B$231-($B$231/10*A226) -> 3.8 | D226: 2 | E226: =E225+D226 -> 17 | F226: =$F$218-E226 -> 2
A227: 9 | B227: 46233 | C227: =$B$231-($B$231/10*A227) -> 1.9 | D227: 1 | E227: =E226+D227 -> 18 | F227: =$F$218-E227 -> 1
A228: 10 | B228: 46234 | C228: =$B$231-($B$231/10*A228) -> 0 | D228: 1 | E228: =E227+D228 -> 19 | F228: =$F$218-E228 -> 0
A230: Summary
A231: Total Story point | B231: 19
A232: Total Completed | B232: =E228 -> 19
A233: Remaining | B233: =B231-E228 -> 0
A234: Completion % | B234: =E228/B231 -> 1

Sheet Timeline
A1: Gantt Chart
F3: Kickoff | G3: Sprint 1 | I3: Sprint 2 | K3: Sprint 3 | M3: Sprint 4 | O3: Sprint 5 | Q3: Submit
A4: Person | B4: Task | C4: Sprint | D4: Est.h | E4: Status (see Backlog) | F4: W1 18 May | G4: W2 25 May | H4: W3 1 Jun | I4: W4 8 Jun | J4: W5 15 Jun | K4: W6 22 Jun | L4: W7 29 Jun | M4: W8 6 Jul | N4: W9 13 Jul | O4: W10 20 Jul | P4: W11 27 Jul | Q4: W12 3 Aug
A5: Nancy
A6: Nancy | B6: Personas & interviews | C6: Sprint 1 | D6: 16 | G6: ● | H6: ●
A7: Nancy | B7: Research competitors | C7: Sprint 1 | D7: 8 | G7: ● | H7: ●
A8: Nancy | B8: Develop early prototypes & mockups | C8: Sprint 1 | D8: 12 | G8: ● | H8: ●
A9: Nancy | B9: Define user stories & acceptance criteria | C9: Sprint 1 | D9: 16 | G9: ● | H9: ●
A10: Nancy | B10: Create budget | C10: Sprint 1 | D10: 10 | G10: ● | H10: ●
A11: Nancy | B11: UX strategy (web vs mobile differentiation) | C11: Sprint 1 | D11: 16 | G11: ● | H11: ●
A12: Nancy | B12: Mid-fidelity wireframes (4 core screens) | C12: Sprint 2 | D12: 16 | I12: ● | J12: ●
A13: Nancy | B13: Sprint 2 ceremonies + retro | C13: Sprint 2 | D13: 6 | I13: ● | J13: ●
A14: Nancy | B14: High-fi mockups (AI-accelerated, core flow) | C14: Sprint 3 | D14: 10 | K14: ● | L14: ●
A15: Nancy | B15: Polish edge cases + empty states | C15: Sprint 3 | D15: 6 | K15: ● | L15: ●
A16: Nancy | B16: User testing prep + recruitment | C16: Sprint 3 | D16: 4 | K16: ● | L16: ●
A17: Nancy | B17: Sprint 3 ceremonies + retro | C17: Sprint 3 | D17: 6 | K17: ● | L17: ●
A18: Nancy | B18: A/B testing setup + 1 design test | C18: Sprint 4 | D18: 10 | M18: ● | N18: ●
A19: Nancy | B19: User testing sessions (target users) | C19: Sprint 4 | D19: 16 | M19: ● | N19: ●
A20: Nancy | B20: Literature review (parallel, continuous) | C20: Sprint 4 | D20: 20 | M20: ● | N20: ●
A21: Nancy | B21: Sprint 4 ceremonies + retro | C21: Sprint 4 | D21: 6 | M21: ● | N21: ●
A22: Nancy | B22: Demo preparation + rehearsal | C22: Sprint 5 | D22: 16 | O22: ● | P22: ●
A23: Nancy | B23: Final paper writing | C23: Sprint 5 | D23: 40 | O23: ● | P23: ●
A24: Nancy | B24: Documentation cleanup | C24: Sprint 5 | D24: 12 | O24: ● | P24: ●
A25: Nancy | B25: Sprint 5 ceremonies + final retro | C25: Sprint 5 | D25: 6 | O25: ● | P25: ●
A27: Hansel
A28: Hansel | B28: Select technologies | C28: Sprint 1 | D28: 8 | G28: ● | H28: ●
A29: Hansel | B29: Create GitHub Repository | C29: Sprint 1 | D29: 4 | G29: ● | H29: ●
A30: Hansel | B30: Define Git workflow | C30: Sprint 1 | D30: 6 | G30: ● | H30: ●
A31: Hansel | B31: Initialise FastAPI backend env | C31: Sprint 1 | D31: 12 | G31: ● | H31: ●
A32: Hansel | B32: Auth API setup (Firebase) | C32: Sprint 2 | D32: 16 | I32: ● | J32: ●
A33: Hansel | B33: POI database schema + initial 30 POIs | C33: Sprint 2 | D33: 20 | I33: ● | J33: ●
A34: Hansel | B34: GET /pois + GET /poi/{id} endpoints | C34: Sprint 2 | D34: 12 | I34: ● | J34: ●
A35: Hansel | B35: POI popularity flag + Save/Unsave POI API | C35: Sprint 2 | D35: 4 | I35: ● | J35: ●
A36: Hansel | B36: AI Planner Spike — API + session memory POC | C36: Sprint 2 | D36: 6 | I36: ● | J36: ●
A37: Hansel | B37: Itinerary generation core engine (AI scheduling) | C37: Sprint 3 | D37: 20 | K37: ● | L37: ●
A38: Hansel | B38: Crowd data integration + API endpoints | C38: Sprint 3 | D38: 16 | K38: ● | L38: ●
A39: Hansel | B39: 5 POI/day + geographic proximity algorithm | C39: Sprint 3 | D39: 12 | K39: ● | L39: ●
A40: Hansel | B40: Integrate ML predictions with backend | C40: Sprint 3 | D40: 12 | K40: ● | L40: ●
A41: Hansel | B41: AI Planner backend (Gemini + session memory) | C41: Sprint 4 | D41: 16 | M41: ● | N41: ●
A42: Hansel | B42: EC2 & Vercel setup | C42: Sprint 4 | D42: 12 | M42: ● | N42: ●
A43: Hansel | B43: Route API integration (Mapbox) | C43: Sprint 4 | D43: 12 | M43: ● | N43: ●
A44: Hansel | B44: Database setup (PostGIS) | C44: Sprint 4 | D44: 16 | M44: ● | N44: ●
A45: Hansel | B45: Performance optimization | C45: Sprint 5 | D45: 16 | O45: ● | P45: ●
A46: Hansel | B46: Final paper writing | C46: Sprint 5 | D46: 40 | O46: ● | P46: ●
A47: Hansel | B47: Documentation cleanup | C47: Sprint 5 | D47: 12 | O47: ● | P47: ●
A48: Hansel | B48: Final deployment + monitoring | C48: Sprint 5 | D48: 12 | O48: ● | P48: ●
A50: Alison
A51: Alison | B51: Crowd data feasibility spike (NYC Open Data) | C51: Sprint 1 | D51: 24 | G51: ● | H51: ●
A52: Alison | B52: Provide data quality report | C52: Sprint 2 | D52: 16 | I52: ● | J52: ●
A53: Alison | B53: Provide preliminary integrated dataset | C53: Sprint 2 | D53: 24 | I53: ● | J53: ●
A54: Alison | B54: Finalised busyness formula and result grade | C54: Sprint 3 | D54: 12 | K54: ● | L54: ●
A55: Alison | B55: ML preparation: Training plan, initial result | C55: Sprint 3 | D55: 20 | K55: ● | L55: ●
A56: Alison | B56: Evaluate ML model (metrics, validation) | C56: Sprint 3 | D56: 12 | K56: ● | L56: ●
A57: Alison | B57: Integrate ML predictions with backend | C57: Sprint 3 | D57: 12 | K57: ● | L57: ●
A58: Alison | B58: Integration testing + bug fixes | C58: Sprint 4 | D58: 24 | M58: ● | N58: ●
A59: Alison | B59: Final user testing + iterations | C59: Sprint 5 | D59: 24 | O59: ● | P59: ●
A60: Alison | B60: Final paper writing | C60: Sprint 5 | D60: 40 | O60: ● | P60: ●
A62: Eoin
A63: Eoin | B63: React-Vite + TypeScript env | C63: Sprint 1 | D63: 12 | G63: ● | H63: ●
A64: Eoin | B64: Initial frontend structure (no features) | C64: Sprint 1 | D64: 8 | G64: ● | H64: ●
A65: Eoin | B65: Auth flow UI (Web) | C65: Sprint 2 | D65: 12 | I65: ● | J65: ●
A66: Eoin | B66: Bottom navigation component (Web) | C66: Sprint 2 | D66: 8 | I66: ● | J66: ●
A67: Eoin | B67: Explore tab UI + Save icon on POI cards (Web) | C67: Sprint 2 | D67: 16 | I67: ● | J67: ●
A68: Eoin | B68: POI Detail page UI (Web) | C68: Sprint 2 | D68: 16 | I68: ● | J68: ●
A69: Eoin | B69: My Itinerary tab shell + date picker (Web) | C69: Sprint 2 | D69: 8 | I69: ● | J69: ●
A70: Eoin | B70: My Itinerary 4-section UI (Web) | C70: Sprint 3 | D70: 20 | K70: ● | L70: ●
A71: Eoin | B71: Itinerary view page (Web) | C71: Sprint 3 | D71: 16 | K71: ● | L71: ●
A72: Eoin | B72: "Why this time" UI (Web) | C72: Sprint 3 | D72: 6 | K72: ● | L72: ●
A73: Eoin | B73: Loading & error states (Web) | C73: Sprint 3 | D73: 6 | K73: ● | L73: ●
A74: Eoin | B74: In-line Itinerary Editor (Web) | C74: Sprint 3 | D74: 12 | K74: ● | L74: ●
A75: Eoin | B75: Saved tab functional (Web) | C75: Sprint 4 | D75: 8 | M75: ● | N75: ●
A76: Eoin | B76: AI Planner UI (Web) | C76: Sprint 4 | D76: 12 | M76: ● | N76: ●
A77: Eoin | B77: Route display component (Web) | C77: Sprint 4 | D77: 10 | M77: ● | N77: ●
A78: Eoin | B78: Filter POIs by interest / accessibility | C78: Sprint 5 | D78: 16 | O78: ● | P78: ●
A79: Eoin | B79: "Surprise Me" entry on Explore | C79: Sprint 5 | D79: 12 | O79: ● | P79: ●
A80: Eoin | B80: Polish UI + animations | C80: Sprint 5 | D80: 20 | O80: ● | P80: ●
A81: Eoin | B81: Final paper writing | C81: Sprint 5 | D81: 40 | O81: ● | P81: ●
A83: Sean
A84: Sean | B84: Mobile env | C84: Sprint 1 | D84: 12 | G84: ● | H84: ●
A85: Sean | B85: Initial frontend structure (no features) | C85: Sprint 1 | D85: 8 | G85: ● | H85: ●
A86: Sean | B86: UX strategy (web vs mobile differentiation) | C86: Sprint 1 | D86: 16 | G86: ● | H86: ●
A87: Sean | B87: Auth flow + Nav (Mobile) | C87: Sprint 2 | D87: 16 | I87: ● | J87: ●
A88: Sean | B88: Explore tab + POI Detail (Mobile) | C88: Sprint 2 | D88: 28 | I88: ● | J88: ●
A89: Sean | B89: My Itinerary tab shell + date picker (Mobile) | C89: Sprint 2 | D89: 6 | I89: ● | J89: ●
A90: Sean | B90: Itinerary view (Mobile) | C90: Sprint 3 | D90: 24 | K90: ● | L90: ●
A91: Sean | B91: "Why this time" + states (Mobile) | C91: Sprint 3 | D91: 16 | K91: ● | L91: ●
A92: Sean | B92: My Itinerary 4-section UI (Mobile) | C92: Sprint 3 | D92: 20 | K92: ● | L92: ●
A93: Sean | B93: In-line Itinerary Editor (Mobile) | C93: Sprint 4 | D93: 6 | M93: ● | N93: ●
A94: Sean | B94: Route display component (Mobile) | C94: Sprint 4 | D94: 10 | M94: ● | N94: ●
A95: Sean | B95: Saved tab functional (Mobile) | C95: Sprint 4 | D95: 8 | M95: ● | N95: ●
A96: Sean | B96: AI Planner UI (Mobile) | C96: Sprint 4 | D96: 12 | M96: ● | N96: ●
A97: Sean | B97: Filter POIs by interest / accessibility | C97: Sprint 5 | D97: 16 | O97: ● | P97: ●
A98: Sean | B98: "Surprise Me" entry on Explore | C98: Sprint 5 | D98: 12 | O98: ● | P98: ●
A99: Sean | B99: Polish UI + animations | C99: Sprint 5 | D99: 20 | O99: ● | P99: ●
A100: Sean | B100: Final paper writing | C100: Sprint 5 | D100: 40 | O100: ● | P100: ●
A103: KEY MILESTONES
A104: 📌 | B104: Sprint 1 Review (in person) | C104: 5 Jun 2026 | H104: ★
A105: 📌 | B105: Sprint 2 Review + Presentations 1+2 | C105: 19 Jun 2026 | J105: ★
A106: 📌 | B106: Sprint 3 Review + Presentations 3+4 | C106: 3 Jul 2026 | L106: ★
A107: 📌 | B107: Sprint 4 Review + Presentations 5+6 | C107: 17 Jul 2026 | N107: ★
...

Sheet Budget
A1: Offpeak — Project Budget
A4: Activity | B4: Budget Base (h) | C4: Planned Hours (Backlog Est.) | D4: Actual Hours (Backlog Real) | E4: Variance (Plan−Actual) | F4: % Used | G4: Buffer 30% (h) | H4: Total Budget (h) | I4: Tools / Services | J4: Actual Cost (€) | K4: Budget Cost (€) | L4: Remaining (€)
A5: 1. Requirements & Research | B5: 41 | C5: =SUMIF(Backlog!$L:$L,"1. Requirements & Research",Backlog!$C:$C) -> 44 | D5: =SUMIF(Backlog!$L:$L,"1. Requirements & Research",Backlog!$D:$D) -> 42 | E5: =C5-D5 -> 2 | F5: =IFERROR(D5/C5,0) -> 0.95454545 | G5: =B5*0.3 -> 12.3 | H5: =B5+G5 -> 53.3 | I5: User interviews, competitor reviews, literature review, POI curation | J5: =D5*20 -> 840 | K5: =H5*20 -> 1066 | L5: =K5-J5 -> 226
A6: 2. Design (UX/UI) | B6: 50 | C6: =SUMIF(Backlog!$L:$L,"2. Design (UX/UI)",Backlog!$C:$C) -> 54 | D6: =SUMIF(Backlog!$L:$L,"2. Design (UX/UI)",Backlog!$D:$D) -> 64 | E6: =C6-D6 -> -10 | F6: =IFERROR(D6/C6,0) -> 1.1851852 | G6: =B6*0.3 -> 15 | H6: =B6+G6 -> 65 | I6: Figma (Free Plan) | J6: =D6*20 -> 1280 | K6: =H6*20 -> 1300 | L6: =K6-J6 -> 20
A7: 3. Backend Development | B7: 111 | C7: =SUMIF(Backlog!$L:$L,"3. Backend Development",Backlog!$C:$C) -> 130 | D7: =SUMIF(Backlog!$L:$L,"3. Backend Development",Backlog!$D:$D) -> 127 | E7: =C7-D7 -> 3 | F7: =IFERROR(D7/C7,0) -> 0.97692308 | G7: =B7*0.3 -> 33.3 | H7: =B7+G7 -> 144.3 | I7: Firebase Auth, FastAPI, PostGIS (Free Tier) | J7: =D7*20 -> 2540 | K7: =H7*20 -> 2886 | L7: =K7-J7 -> 346
A8: 4. Web Frontend | B8: 206 | C8: =SUMIF(Backlog!$L:$L,"4. Web Frontend",Backlog!$C:$C) -> 204 | D8: =SUMIF(Backlog!$L:$L,"4. Web Frontend",Backlog!$D:$D) -> 204 | E8: =C8-D8 -> 0 | F8: =IFERROR(D8/C8,0) -> 1 | G8: =B8*0.3 -> 61.8 | H8: =B8+G8 -> 267.8 | I8: React-Vite, Vercel (Free Tier) | J8: =D8*20 -> 4080 | K8: =H8*20 -> 5356 | L8: =K8-J8 -> 1276
A9: 5. Mobile Development | B9: 146 | C9: =SUMIF(Backlog!$L:$L,"5. Mobile Development",Backlog!$C:$C) -> 160 | D9: =SUMIF(Backlog!$L:$L,"5. Mobile Development",Backlog!$D:$D) -> 112 | E9: =C9-D9 -> 48 | F9: =IFERROR(D9/C9,0) -> 0.7 | G9: =B9*0.3 -> 43.8 | H9: =B9+G9 -> 189.8 | I9: React Native / PWA | J9: =D9*20 -> 2240 | K9: =H9*20 -> 3796 | L9: =K9-J9 -> 1556
A10: 6. ML / Data Engineering | B10: 175 | C10: =SUMIF(Backlog!$L:$L,"6. ML / Data Engineering",Backlog!$C:$C) -> 190 | D10: =SUMIF(Backlog!$L:$L,"6. ML / Data Engineering",Backlog!$D:$D) -> 206 | E10: =C10-D10 -> -16 | F10: =IFERROR(D10/C10,0) -> 1.0842105 | G10: =B10*0.3 -> 52.5 | H10: =B10+G10 -> 227.5 | I10: NYC Open Data, Prophet/Pandas (open source), Gemini API | J10: =D10*20 -> 4120 | K10: =H10*20 -> 4550 | L10: =K10-J10 -> 430
A11: 7. Integration | B11: 11 | C11: =SUMIF(Backlog!$L:$L,"7. Integration",Backlog!$C:$C) -> 0 | D11: =SUMIF(Backlog!$L:$L,"7. Integration",Backlog!$D:$D) -> 0 | E11: =C11-D11 -> 0 | F11: =IFERROR(D11/C11,0) -> 0 | G11: =B11*0.3 -> 3.3 | H11: =B11+G11 -> 14.3 | I11: Mapbox Directions API (Free Tier) | J11: =D11*20 -> 0 | K11: =H11*20 -> 286 | L11: =K11-J11 -> 286
A12: 8. Testing & QA | B12: 72 | C12: =SUMIF(Backlog!$L:$L,"8. Testing & QA",Backlog!$C:$C) -> 74 | D12: =SUMIF(Backlog!$L:$L,"8. Testing & QA",Backlog!$D:$D) -> 74 | E12: =C12-D12 -> 0 | F12: =IFERROR(D12/C12,0) -> 1 | G12: =B12*0.3 -> 21.6 | H12: =B12+G12 -> 93.6 | I12: User testing sessions with target users | J12: =D12*20 -> 1480 | K12: =H12*20 -> 1872 | L12: =K12-J12 -> 392
A13: 9. Deployment & DevOps | B13: 31 | C13: =SUMIF(Backlog!$L:$L,"9. Deployment & DevOps",Backlog!$C:$C) -> 34 | D13: =SUMIF(Backlog!$L:$L,"9. Deployment & DevOps",Backlog!$D:$D) -> 33 | E13: =C13-D13 -> 1 | F13: =IFERROR(D13/C13,0) -> 0.97058824 | G13: =B13*0.3 -> 9.3 | H13: =B13+G13 -> 40.3 | I13: AWS EC2 (Free Tier), Vercel hosting | J13: =D13*20 -> 660 | K13: =H13*20 -> 806 | L13: =K13-J13 -> 146
A14: 10. Project Management | B14: 109 | C14: =SUMIF(Backlog!$L:$L,"10. Project Management",Backlog!$C:$C) -> 138 | D14: =SUMIF(Backlog!$L:$L,"10. Project Management",Backlog!$D:$D) -> 136 | E14: =C14-D14 -> 2 | F14: =IFERROR(D14/C14,0) -> 0.98550725 | G14: =B14*0.3 -> 32.7 | H14: =B14+G14 -> 141.7 | I14: Trello, Google Drive, Slack (free), Overleaf (LaTeX) | J14: =D14*20 -> 2720 | K14: =H14*20 -> 2834 | L14: =K14-J14 -> 114
A15: TOTAL | B15: =SUM(B5:B14) -> 952 | C15: =SUM(C5:C14) -> 1028 | D15: =SUM(D5:D14) -> 998 | E15: =C15-D15 -> 30 | F15: =IFERROR(D15/C15,0) -> 0.97081712 | G15: =SUM(G5:G14) -> 285.6 | H15: =SUM(H5:H14) -> 1237.6 | J15: =SUM(J5:J14) -> 19960 | K15: =SUM(K5:K14) -> 24752 | L15: =K15-J15 -> 4792
